llama_index/vector_stores/azure_postgres/__init__.py
llama_index/vector_stores/azure_postgres/base.py
llama_index/vector_stores/azure_postgres/common/__init__.py
llama_index/vector_stores/azure_postgres/common/_base.py
llama_index/vector_stores/azure_postgres/common/_connection.py
llama_index/vector_stores/azure_postgres/common/_shared.py
llama_index/vector_stores/azure_postgres/common/aio/__init__.py
llama_index/vector_stores/azure_postgres/common/aio/_connection.py
llama_index_vector_stores_azurepostgres-0.2.0.dist-info/METADATA
llama_index_vector_stores_azurepostgres-0.2.0.dist-info/WHEEL
llama_index_vector_stores_azurepostgres-0.2.0.dist-info/RECORD
