Metadata-Version: 2.4
Name: llama-index-vector-stores-azurepostgres
Version: 0.2.0
Summary: AI framework integrations for Azure Database for PostgreSQL
Author-email: Arda Aytekin <8845951+aytekinar@users.noreply.github.com>, Orhan Kislal <kislalorhan@microsoft.com>
License: MIT
Keywords: azure,database,llamaindex,postgresql,vectorstore
Requires-Dist: aiohttp~=3.0
Requires-Dist: azure-identity~=1.0
Requires-Dist: llama-index-core<0.15,>=0.13
Requires-Dist: numpy~=2.0
Requires-Dist: pgvector~=0.4.0
Requires-Dist: psycopg[binary,pool]~=3.0
Requires-Dist: pydantic~=2.0
Requires-Dist: typing-extensions~=4.0; python_version < '3.12'
